mouselock/__init__.py
mouselock/main.py
mouselock-0.2.dist-info/METADATA
mouselock-0.2.dist-info/WHEEL
mouselock-0.2.dist-info/top_level.txt
mouselock-0.2.dist-info/RECORD
