Metadata-Version: 2.1
Name: mouselock
Version: 0.2
Summary: A Python package for easily and programmatically locking your mouse.
